verilog/Sequential/counter/src/counter.v
module counter (
    input wire rst,
    input wire clk,

    output reg [2:0]q
);
always @(posedge clk or negedge rst) begin
    if(~rst) begin
      q<=3'b000;
    end
    
    else begin
        q=4+q;
    end

end


endmodule

verilog/Sequential/counter/tb/counter_tb.v
module counter_tb ();
  
  reg rst;
  reg clk;

  wire [2:0]q;

counter u_gate(
    .rst(rst),
    .clk(clk),
    .q(q)
);

initial begin
    rst=0;
    clk=0;
    #10;
    rst=1;
    #200;
    $finish;
end

initial begin
   $dumpfile("temp/counter.vcd");
   $dumpvars(0,counter_tb); 
end

always begin
    #5 clk=~clk;  
end


    
endmodule

verilog/Sequential/counter/temp/counter.vcd
$date
	Thu Sep 12 13:05:11 2024
$end
$version
	Icarus Verilog
$end
$timescale
	1s
$end
$scope module counter_tb $end
$var wire 3 ! q [2:0] $end
$var reg 1 " clk $end
$var reg 1 # rst $end
$scope module u_gate $end
$var wire 1 " clk $end
$var wire 1 # rst $end
$var reg 3 $ q [2:0] $end
$upscope $end
$upscope $end
$enddefinitions $end
#0
$dumpvars
b0 $
0#
0"
b0 !
$end
#5
1"
#10
0"
1#
#15
b100 !
b100 $
1"
#20
0"
#25
b0 !
b0 $
1"
#30
0"
#35
b100 !
b100 $
1"
#40
0"
#45
b0 !
b0 $
1"
#50
0"
#55
b100 !
b100 $
1"
#60
0"
#65
b0 !
b0 $
1"
#70
0"
#75
b100 !
b100 $
1"
#80
0"
#85
b0 !
b0 $
1"
#90
0"
#95
b100 !
b100 $
1"
#100
0"
#105
b0 !
b0 $
1"
#110
0"
#115
b100 !
b100 $
1"
#120
0"
#125
b0 !
b0 $
1"
#130
0"
#135
b100 !
b100 $
1"
#140
0"
#145
b0 !
b0 $
1"
#150
0"
#155
b100 !
b100 $
1"
#160
0"
#165
b0 !
b0 $
1"
#170
0"
#175
b100 !
b100 $
1"
#180
0"
#185
b0 !
b0 $
1"
#190
0"
#195
b100 !
b100 $
1"
#200
0"
#205
b0 !
b0 $
1"
